AUTHORS
LICENSE
MANIFEST.in
README.rst
setup.py
markdown_viewer.egg-info/PKG-INFO
markdown_viewer.egg-info/SOURCES.txt
markdown_viewer.egg-info/dependency_links.txt
markdown_viewer.egg-info/entry_points.txt
markdown_viewer.egg-info/top_level.txt
mdviewer/__init__.py
mdviewer/viewer.py